.DS_Store
bbscrape/__init__.py
bbscrape/__main__.py
bbscrape/baseball_reference.py
bbscrape/fangraphs.py
bbscrape/http.py
bbscrape/spotrac.py
bbscrape/tables.py
bbsim/__init__.py
bbsim/__main__.py
bbsim/advcalc.py
bbsim/aggstat.py
bbsim/appearance.py
bbsim/batting.py
bbsim/fielding.py
bbsim/gamescore.py
bbsim/gappear.py
bbsim/pitching.py
bbsim/player.py
bbsim/rbi.py
bbsim/runsper.py
bbsim/woba.py
bbsim/core/__init__.py
bbsim/core/game.py
bbsim/core/handed.py
bbsim/core/roster.py
bbsim/core/stat.py
bbsim/data/__init__.py
bbsim/data/lib.py
bbsim/data/season.py
bbsim/index/__init__.py
bbsim/index/core.py
bbsim/index/lookup.py
bbsim/index/slice.py
bbsim/index/util.py
bbsim/matrix/__init__.py
bbsim/matrix/core.py
bbsim/matrix/rem.py
bbsim/matrix/slice.py
bbsim/matrix/util.py
bbcmd-1.2.dist-info/LICENSE
bbcmd-1.2.dist-info/METADATA
bbcmd-1.2.dist-info/WHEEL
bbcmd-1.2.dist-info/entry_points.txt
bbcmd-1.2.dist-info/top_level.txt
bbcmd-1.2.dist-info/RECORD
