Metadata-Version: 2.1
Name: bbcmd
Version: 1.2
Summary: Baseball Statistics Simulator
Home-page: https://github.com/luciancooper/bbcmd
Author: Lucian Cooper
License: MIT
Keywords: baseball statistics sabermetrics
Platform: UNKNOWN
Classifier: Intended Audience :: Developers
Classifier: Intended Audience :: Science/Research
Classifier: License :: OSI Approved :: MIT License
Classifier: Programming Language :: Python
Classifier: Programming Language :: Python :: 3.6
Classifier: Operating System :: MacOS
Classifier: Operating System :: Microsoft :: Windows
Classifier: Operating System :: POSIX :: Linux
Requires-Dist: cmdprogress
Requires-Dist: numpy
Requires-Dist: pandas
Requires-Dist: beautifulsoup4
